nazobase/MediaInfoVS.py
nazobase/__init__.py
nazobase/base.py
nazobase/mvsfunc1610.py
nazobase/nazolib.cp37-win_amd64.pyd
nazobase/options.py
nazobase-0.2.1.dist-info/LICENSE
nazobase-0.2.1.dist-info/METADATA
nazobase-0.2.1.dist-info/WHEEL
nazobase-0.2.1.dist-info/top_level.txt
nazobase-0.2.1.dist-info/RECORD
