Metadata-Version: 2.1
Name: nazobase
Version: 0.2.1
Summary: NAZOrip basement where deposits some easy functions for Vapoursynth. - GoodManWEN/nazobase
Home-page: https://www.nazorip.site
Author: WEN
License: UNKNOWN
Keywords: vapoursynth,nazobase,NAZOrip
Platform: UNKNOWN
Classifier: Programming Language :: Python :: 3.6
Classifier: Programming Language :: Python :: 3.7
Classifier: License :: OSI Approved :: GNU Affero General Public License v3 or later (AGPLv3+)
Classifier: Operating System :: Microsoft :: Windows
Requires-Python: >=3.7
Requires-Dist: pymediainfo
